odoo/addons/purchase_security/README.rst
odoo/addons/purchase_security/__init__.py
odoo/addons/purchase_security/__manifest__.py
odoo/addons/purchase_security/i18n/it.po
odoo/addons/purchase_security/i18n/purchase_security.pot
odoo/addons/purchase_security/readme/CONFIGURATION.rst
odoo/addons/purchase_security/readme/CONTRIBUTORS.rst
odoo/addons/purchase_security/readme/DESCRIPTION.rst
odoo/addons/purchase_security/readme/USAGE.rst
odoo/addons/purchase_security/security/security.xml
odoo/addons/purchase_security/static/description/icon.png
odoo/addons/purchase_security/static/description/index.html
odoo/addons/purchase_security/tests/__init__.py
odoo/addons/purchase_security/tests/test_access_rights.py
odoo14_addon_purchase_security-14.0.1.0.1.dev3.dist-info/METADATA
odoo14_addon_purchase_security-14.0.1.0.1.dev3.dist-info/WHEEL
odoo14_addon_purchase_security-14.0.1.0.1.dev3.dist-info/top_level.txt
odoo14_addon_purchase_security-14.0.1.0.1.dev3.dist-info/RECORD
